scherry/cli/__main__.py
scherry/cli/appdata.py
scherry/cli/bucket.py
scherry/cli/runner.py
scherry/cli/script.py
scherry/core/__init__.py
scherry/core/bucket.py
scherry/core/caching.py
scherry/core/ctx.py
scherry/core/mgr.py
scherry/core/model.py
scherry/helper/__main__.py
scherry/helper/bucket.py
scherry/helper/utils.py
scherry/utils/auto_save_dict.py
scherry/utils/dictionary.py
scherry/utils/file.py
scherry/utils/gen_parse.py
scherry/utils/git.py
scherry/utils/hashing.py
scherry/utils/logging.py
scherry/utils/zip.py
scherry-0.1.2.dist-info/LICENSE
scherry-0.1.2.dist-info/METADATA
scherry-0.1.2.dist-info/WHEEL
scherry-0.1.2.dist-info/entry_points.txt
scherry-0.1.2.dist-info/top_level.txt
scherry-0.1.2.dist-info/RECORD
