Metadata-Version: 2.1
Name: scherry
Version: 0.1.2
Requires-Python: >=3.7
License-File: LICENSE
Requires-Dist: requests
Requires-Dist: click
Requires-Dist: orjson
Requires-Dist: parse
Requires-Dist: toml
